mpra/__init__.py
mpra/mpra.py
mpra-0.1.1.dist-info/METADATA
mpra-0.1.1.dist-info/WHEEL
mpra-0.1.1.dist-info/top_level.txt
mpra-0.1.1.dist-info/RECORD
