Metadata-Version: 2.1
Name: mpra
Version: 0.1.1
Summary: MPRA - Multipurpose Resource Automation
Home-page: https://github.com/ManojPennada/mpra
Author: Manoj Pennada
Author-email: manojpennada@gmail.com
Classifier: Programming Language :: Python :: 3
Classifier: License :: OSI Approved :: MIT License
Classifier: Operating System :: OS Independent
Requires-Python: >=3.6
